pymaschine/__init__.py
pymaschine/__main__.py
pymaschine/engine.py
pymaschine/maschine.py
pymaschine/ui.py
pymaschine/utils.py
pymaschine/modules/__init__.py
pymaschine/modules/pad_layout.py
pymaschine/modules/pattern.py
pymaschine/modules/project.json
pymaschine/modules/project.py
pymaschine/modules/search_sound.py
pymaschine-0.0.3.dist-info/METADATA
pymaschine-0.0.3.dist-info/WHEEL
pymaschine-0.0.3.dist-info/entry_points.txt
pymaschine-0.0.3.dist-info/top_level.txt
pymaschine-0.0.3.dist-info/RECORD
